alumath_kheoml/__init__.py
alumath_kheoml/matrix.py
alumath_kheoml-0.1.1.dist-info/METADATA
alumath_kheoml-0.1.1.dist-info/WHEEL
alumath_kheoml-0.1.1.dist-info/top_level.txt
alumath_kheoml-0.1.1.dist-info/RECORD
