Metadata-Version: 2.4
Name: alumath_kheoml
Version: 0.1.1
Summary: A matrix operations library developed by alumath_kheoml group at African Leadership University
Home-page: https://github.com/oreste-abizera/ALU-BSE-MathML-PCA-Assignment-group4
Author: Group 4
Author-email: your.email@example.com
Classifier: Programming Language :: Python :: 3
Classifier: Operating System :: OS Independent
Classifier: Topic :: Scientific/Engineering :: Mathematics
Classifier: Intended Audience :: Education
Classifier: Intended Audience :: Science/Research
Requires-Python: >=3.6
Requires-Dist: numpy>=1.19.0
Dynamic: author
Dynamic: author-email
Dynamic: classifier
Dynamic: description
Dynamic: description-content-type
Dynamic: home-page
Dynamic: requires-dist
Dynamic: requires-python
Dynamic: summary
